{
  "0": {
  "id": "0",
  "Chinese": "你今天负责检查来入住的旅客有没有问题",
  "English": "You are responsible for checking if there are any issues with the guests checking in today.",
  "Thailand": "คุณรับผิดชอบตรวจสอบว่ามีปัญหากับแขกที่เช็คอินวันนี้หรือไม่",
  "Indonasia": "Anda bertanggung jawab untuk memeriksa apakah ada masalah dengan tamu yang check-in hari ini.",
  "Chinese_tw": "你今天負責檢查來入住的旅客有沒有問題",
  "Malay": "Anda bertanggungjawab untuk memeriksa jika terdapat sebarang masalah dengan tetamu yang mendaftar hari ini.",
  "Vietnamese": "Hôm nay bạn chịu trách nhiệm kiểm tra xem khách đến có vấn đề gì không",
  "Japanese": "今日はチェックインするお客様に問題がないか確認する担当です",
  "Korean": "오늘 체크인하는 손님에게 문제가 없는지 확인하는 일을 맡고 있어요",
  "Russian": "Сегодня ты отвечаешь за проверку, есть ли у прибывающих гостей проблемы",
  "Hindi": "आज आप यह जांचने के लिए जिम्मेदार हैं कि आने वाले मेहमानों को कोई समस्या है या नहीं",
  "Portuguese": "Hoje você é responsável por verificar se os hóspedes que estão chegando têm algum problema.",
  "Spanish": "Hoy eres responsable de comprobar si los huéspedes que llegan tienen algún problema.",
  "German": "Heute bist du dafür verantwortlich zu überprüfen, ob die ankommenden Gäste Probleme haben.",
  "French": "Aujourd'hui, vous êtes responsable de vérifier si les clients qui arrivent ont des problèmes.",
  "Arabic": "أنت مسؤول اليوم عن التحقق مما إذا كان لدى الضيوف القادمين أي مشاكل."
},
  "1": {
  "id": "1",
  "Chinese": "你好呀，我来办理入住",
  "English": "Hello, I am here to check in.",
  "Thailand": "สวัสดีค่ะ ฉันมาที่นี่เพื่อเช็คอิน",
  "Indonasia": "Halo, saya datang untuk check-in.",
  "Chinese_tw": "你好呀，我來辦理入住",
  "Malay": "Hai, saya datang untuk mendaftar.",
  "Vietnamese": "Xin chào, tôi đến để làm thủ tục nhận phòng",
  "Japanese": "こんにちは、チェックインをしに来ました",
  "Korean": "안녕하세요, 체크인하러 왔어요",
  "Russian": "Здравствуйте, я пришел для регистрации",
  "Hindi": "नमस्ते, मैं चेक-इन करने आया हूँ",
  "Portuguese": "Olá, vim fazer o check-in.",
  "Spanish": "Hola, vengo a hacer el check-in.",
  "German": "Hallo, ich komme zum Einchecken.",
  "French": "Bonjour, je viens faire le check-in.",
  "Arabic": "مرحبًا، جئت لإجراء تسجيل الوصول."
},
  "2": {
  "id": "2",
  "Chinese": "这是我的发饰呀",
  "English": "This is my hair accessory.",
  "Thailand": "นี่คือเครื่องประดับผมของฉัน",
  "Indonasia": "Ini adalah aksesori rambut saya.",
  "Chinese_tw": "這是我的髮飾呀",
  "Malay": "Ini adalah aksesori rambut saya.",
  "Vietnamese": "Đây là phụ kiện tóc của tôi nè",
  "Japanese": "これは私のヘアアクセサリーです",
  "Korean": "이건 제 헤어 액세서리예요",
  "Russian": "Это мой аксессуар для волос",
  "Hindi": "यह मेरा हेयर एक्सेसरी है",
  "Portuguese": "Este é meu acessório de cabelo.",
  "Spanish": "Este es mi accesorio para el cabello.",
  "German": "Das ist mein Haarschmuck.",
  "French": "C'est mon accessoire pour les cheveux.",
  "Arabic": "هذا هو زيني للشعر."
},
  "3": {
  "id": "3",
  "Chinese": "这是我的手套啦",
  "English": "These are my gloves.",
  "Thailand": "นี่คือถุงมือของฉัน",
  "Indonasia": "Ini adalah sarung tangan saya.",
  "Chinese_tw": "這是我的手套啦",
  "Malay": "Ini adalah sarung tangan saya.",
  "Vietnamese": "Đây là găng tay của tôi đây",
  "Japanese": "これは私の手袋です",
  "Korean": "이건 제 장갑이에요",
  "Russian": "Это мои перчатки",
  "Hindi": "यह मेरे दस्ताने हैं",
  "Portuguese": "Estas são minhas luvas.",
  "Spanish": "Estos son mis guantes.",
  "German": "Das sind meine Handschuhe.",
  "French": "Ce sont mes gants.",
  "Arabic": "هذه هي قفازاتي."
},
  "4": {
  "id": "4",
  "Chinese": "戴口罩是为了防寒啦",
  "English": "Wearing a mask is to keep warm.",
  "Thailand": "การใส่หน้ากากเป็นการป้องกันความหนาว",
  "Indonasia": "Memakai masker adalah untuk menghangatkan diri.",
  "Chinese_tw": "戴口罩是為了防寒啦",
  "Malay": "Memakai topeng adalah untuk menghangatkan diri.",
  "Vietnamese": "Đeo khẩu trang là để giữ ấm đó",
  "Japanese": "マスクをつけるのは寒さ対策です",
  "Korean": "마스크를 쓰는 것은 추위를 막기 위해서예요",
  "Russian": "Ношение маски нужно для защиты от холода",
  "Hindi": "मास्क पहनना ठंड से बचने के लिए है",
  "Portuguese": "Usar máscara é para me proteger do frio.",
  "Spanish": "Usar mascarilla es para protegerme del frío.",
  "German": "Eine Maske zu tragen ist, um mich vor der Kälte zu schützen.",
  "French": "Porter un masque est pour me protéger du froid.",
  "Arabic": "ارتداء الكمامة هو لحماية من البرد."
},
  "5": {
  "id": "5",
  "Chinese": "这是我的小猫，可爱吗",
  "English": "This is my kitten, isn't it cute?",
  "Thailand": "นี่คือแมวตัวน้อยของฉัน น่ารักไหม",
  "Indonasia": "Ini kucing kecil saya, lucu kan?",
  "Chinese_tw": "這是我的小貓，可愛嗎",
  "Malay": "Ini kucing kecil saya, comel tak?",
  "Vietnamese": "Đây là mèo con của tôi, dễ thương không?",
  "Japanese": "これは私の子猫、可愛いでしょう？",
  "Korean": "이건 제 아기 고양이에요, 귀엽죠?",
  "Russian": "Это мой котенок, милый, правда?",
  "Hindi": "यह मेरी बिल्ली का बच्चा है, क्या यह प्यारा नहीं है?",
  "Portuguese": "Este é meu gatinho, ele é fofo?",
  "Spanish": "Este es mi gatito, ¿es lindo?",
  "German": "Das ist meine Katze, ist sie süß?",
  "French": "C'est mon petit chat, il est mignon ?",
  "Arabic": "هذا هو قطتي، هل هو لطيف؟"
},
  "6": {
  "id": "6",
  "Chinese": "辛苦你啦",
  "English": "Thank you for your hard work.",
  "Thailand": "ขอบคุณสำหรับความพยายามของคุณ",
  "Indonasia": "Terima kasih atas kerja kerasmu.",
  "Chinese_tw": "辛苦你啦",
  "Malay": "Terima kasih atas usaha anda.",
  "Vietnamese": "Cảm ơn bạn đã vất vả",
  "Japanese": "お疲れ様です",
  "Korean": "수고 많으세요",
  "Russian": "Спасибо за вашу работу",
  "Hindi": "आपका बहुत धन्यवाद",
  "Portuguese": "Obrigado pelo seu trabalho.",
  "Spanish": "Gracias por tu esfuerzo.",
  "German": "Danke für deine Mühe.",
  "French": "Merci pour votre travail.",
  "Arabic": "شكرًا لك على مجهودك."
},
  "7": {
  "id": "7",
  "Chinese": "为什么不让我进去，我要举报你们",
  "English": "Why won't you let me in? I want to report you.",
  "Thailand": "ทำไมคุณไม่ให้ฉันเข้าไป ฉันต้องการแจ้งความ",
  "Indonasia": "Mengapa kamu tidak membiarkan saya masuk? Saya ingin melaporkan kalian.",
  "Chinese_tw": "為什麼不讓我進去，我要舉報你們",
  "Malay": "Kenapa anda tidak membenarkan saya masuk? Saya mahu melaporkan anda.",
  "Vietnamese": "Tại sao không cho tôi vào, tôi muốn báo cáo các bạn",
  "Japanese": "なぜ入れてくれないの？あなたたちを通報したい",
  "Korean": "왜 저를 들어가게 해주지 않나요? 신고할 거예요",
  "Russian": "Почему вы не пускаете меня внутрь? Я хочу вас пожаловаться",
  "Hindi": "क्यों मुझे अंदर नहीं जाने दे रहे, मैं आपकी शिकायत करना चाहता हूँ",
  "Portuguese": "Por que não posso entrar? Eu quero denunciar vocês.",
  "Spanish": "¿Por qué no me dejas entrar? Quiero denunciarlos.",
  "German": "Warum darf ich nicht rein? Ich möchte euch melden.",
  "French": "Pourquoi ne puis-je pas entrer ? Je veux vous dénoncer.",
  "Arabic": "لماذا لا تتركني أدخل؟ أريد الإبلاغ عنكم."
},
  "8": {
  "id": "8",
  "Chinese": "你好，办理下入住",
  "English": "Hello, I would like to check in.",
  "Thailand": "สวัสดีค่ะ ฉันต้องการเช็คอิน",
  "Indonasia": "Halo, saya ingin check-in.",
  "Chinese_tw": "你好，辦理下入住",
  "Malay": "Hai, saya ingin mendaftar.",
  "Vietnamese": "Xin chào, làm thủ tục nhận phòng giúp tôi",
  "Japanese": "こんにちは、チェックインをお願いします",
  "Korean": "안녕하세요, 체크인 좀 해주세요",
  "Russian": "Здравствуйте, помогите мне зарегистрироваться",
  "Hindi": "नमस्ते, कृपया मेरा चेक-इन करें",
  "Portuguese": "Olá, quero fazer o check-in.",
  "Spanish": "Hola, quiero hacer el check-in.",
  "German": "Hallo, ich möchte einchecken.",
  "French": "Bonjour, je viens faire le check-in.",
  "Arabic": "مرحبًا، أريد إجراء تسجيل الوصول."
},
  "9": {
  "id": "9",
  "Chinese": "我戴了美瞳",
  "English": "I am wearing colored contact lenses.",
  "Thailand": "ฉันใส่คอนแทคเลนส์สี",
  "Indonasia": "Saya memakai lensa kontak berwarna.",
  "Chinese_tw": "我戴了美瞳",
  "Malay": "Saya memakai kanta lekap berwarna.",
  "Vietnamese": "Tôi đang đeo kính áp tròng",
  "Japanese": "私はカラコンをつけています",
  "Korean": "저는 컬러 렌즈를 끼고 있어요",
  "Russian": "Я ношу цветные контактные линзы",
  "Hindi": "मैंने रंगीन कॉन्टैक्ट लेंस पहने हैं",
  "Portuguese": "Estou usando lentes de contato coloridas.",
  "Spanish": "Llevo lentes de contacto de colores.",
  "German": "Ich trage farbige Kontaktlinsen.",
  "French": "Je porte des lentilles de contact colorées.",
  "Arabic": "أنا أرتدي عدسات ملونة."
},
  "10": {
  "id": "10",
  "Chinese": "这尖牙是我的假牙",
  "English": "These sharp teeth are my dentures",
  "Thailand": "ฟันแหลมคมเหล่านี้คือฟันปลอมของฉัน",
  "Indonasia": "Gigi tajam ini adalah gigi palsu saya",
  "Chinese_tw": "這尖牙是我的假牙",
  "Malay": "Gigi tajam ini adalah gigi palsu saya",
  "Vietnamese": "Chiếc răng nhọn này là răng giả của tôi",
  "Japanese": "この尖った歯は私の義歯です",
  "Korean": "이 뾰족한 이는 내 의치입니다",
  "Russian": "Этот острый зуб - мой протез",
  "Hindi": "यह नुकीला दांत मेरी नकली दांत है",
  "Portuguese": "Este dente afiado é meu dente falso",
  "Spanish": "Este colmillo es mi diente falso",
  "German": "Dieser Fangzahn ist mein Zahnersatz",
  "French": "Cette dent pointue est ma prothèse dentaire",
  "Arabic": "هذا الناب هو سنّي الاصطناعي"
},
  "11": {
  "id": "11",
  "Chinese": "我只是不喜欢大蒜的味道",
  "English": "I just don't like the taste of garlic",
  "Thailand": "ฉันแค่ไม่ชอบรสชาติของกระเทียม",
  "Indonasia": "Saya hanya tidak suka rasa bawang putih",
  "Chinese_tw": "我只是不喜歡大蒜的味道",
  "Malay": "Saya hanya tidak suka rasa bawang putih",
  "Vietnamese": "Tôi chỉ không thích mùi tỏi",
  "Japanese": "私はただニンニクの匂いが好きではありません",
  "Korean": "나는 단지 마늘 냄새가 싫을 뿐입니다",
  "Russian": "Мне просто не нравится запах чеснока",
  "Hindi": "मुझे बस लहसुन की गंध पसंद नहीं है",
  "Portuguese": "Eu só não gosto do gosto de alho",
  "Spanish": "Solo no me gusta el sabor del ajo",
  "German": "Ich mag einfach den Geschmack von Knoblauch nicht",
  "French": "Je n'aime tout simplement pas le goût de l'ail",
  "Arabic": "أنا فقط لا أحب طعم الثوم"
},
  "12": {
  "id": "12",
  "Chinese": "不让我进去我就把你同化",
  "English": "If you don't let me in, I'll assimilate you",
  "Thailand": "ถ้าไม่ให้ฉันเข้าไป ฉันจะทำให้คุณกลายเป็นหนึ่งเดียวกับฉัน",
  "Indonasia": "Jika kamu tidak membiarkan saya masuk, saya akan mengasimilasi kamu",
  "Chinese_tw": "不讓我進去我就把你同化",
  "Malay": "Jika kamu tidak membiarkan saya masuk, saya akan menyatukan kamu",
  "Vietnamese": "Nếu không cho tôi vào, tôi sẽ đồng hóa bạn",
  "Japanese": "入れてくれないなら、あなたを同化します",
  "Korean": "들어가게 해주지 않으면 당신을 동화시킬 것입니다",
  "Russian": "Если не пустишь меня внутрь, я тебя ассимилирую",
  "Hindi": "अगर तुम मुझे अंदर नहीं आने दोगे, तो मैं तुम्हें समाहित कर दूंगा",
  "Portuguese": "Se você não me deixar entrar, eu vou te assimilar",
  "Spanish": "Si no me dejas entrar, te voy a asimilar",
  "German": "Wenn du mich nicht reinlässt, assimilier ich dich",
  "French": "Si tu ne me laisses pas entrer, je vais te assimiler",
  "Arabic": "إذا لم تتركني أدخل، سأقوم بدمجك"
},
  "13": {
  "id": "13",
  "Chinese": "救命，居然用大蒜攻击我",
  "English": "Help, they're attacking me with garlic",
  "Thailand": "ช่วยด้วย พวกเขากำลังโจมตีฉันด้วยกระเทียม",
  "Indonasia": "Tolong, mereka menyerang saya dengan bawang putih",
  "Chinese_tw": "救命，居然用大蒜攻擊我",
  "Malay": "Tolong, mereka menyerang saya dengan bawang putih",
  "Vietnamese": "Cứu tôi với, sao lại dùng tỏi tấn công tôi",
  "Japanese": "助けて、まさかニンニクで攻撃されるなんて",
  "Korean": "도와줘, 마늘로 공격하다니",
  "Russian": "Спасите, как можно атаковать меня чесноком",
  "Hindi": "बचाओ, मुझे लहसुन से हमला किया जा रहा है",
  "Portuguese": "Socorro, estão me atacando com alho",
  "Spanish": "¡Ayuda, me están atacando con ajo!",
  "German": "Hilfe, sie greifen mich mit Knoblauch an",
  "French": "Au secours, on m'attaque avec de l'ail",
  "Arabic": "نجدة، إنهم يهاجمونني بالثوم"
},
  "14": {
  "id": "14",
  "Chinese": "我不怕这个",
  "English": "I'm not afraid of this",
  "Thailand": "ฉันไม่กลัวสิ่งนี้",
  "Indonasia": "Saya tidak takut dengan ini",
  "Chinese_tw": "我不怕這個",
  "Malay": "Saya tidak takut dengan ini",
  "Vietnamese": "Tôi không sợ cái này",
  "Japanese": "私はこれを恐れていません",
  "Korean": "나는 이걸 두렵지 않아",
  "Russian": "Я этого не боюсь",
  "Hindi": "मुझे इससे डर नहीं लगता",
  "Portuguese": "Eu não tenho medo disso",
  "Spanish": "No tengo miedo de esto",
  "German": "Ich habe keine Angst davor",
  "French": "Je n'ai pas peur de ça",
  "Arabic": "لا أخاف من هذا"
},
  "15": {
  "id": "15",
  "Chinese": "谢谢你",
  "English": "Thank you",
  "Thailand": "ขอบคุณนะ",
  "Indonasia": "Terima kasih",
  "Chinese_tw": "謝謝你",
  "Malay": "Terima kasih",
  "Vietnamese": "Cảm ơn bạn",
  "Japanese": "ありがとう",
  "Korean": "고마워",
  "Russian": "Спасибо тебе",
  "Hindi": "धन्यवाद",
  "Portuguese": "Obrigado",
  "Spanish": "Gracias",
  "German": "Danke dir",
  "French": "Merci",
  "Arabic": "شكراً لك"
},
  "16": {
  "id": "16",
  "Chinese": "晚上好，宝贝",
  "English": "Good evening, baby",
  "Thailand": "สวัสดีตอนเย็นที่รัก",
  "Indonasia": "Selamat malam, sayang",
  "Chinese_tw": "晚上好，寶貝",
  "Malay": "Selamat malam, sayang",
  "Vietnamese": "Chào buổi tối, cưng",
  "Japanese": "こんばんは、ベイビー",
  "Korean": "안녕하세요, 자기야",
  "Russian": "Добрый вечер, дорогая",
  "Hindi": "शाम शुभ हो, बेबी",
  "Portuguese": "Boa noite, querida",
  "Spanish": "Buenas noches, cariño",
  "German": "Guten Abend, Schatz",
  "French": "Bonsoir, mon chéri",
  "Arabic": "مساء الخير، حبيبي"
},
  "17": {
  "id": "17",
  "Chinese": "我的手表好看吗",
  "English": "Does my watch look good?",
  "Thailand": "นาฬิกาของฉันดูดีไหม",
  "Indonasia": "Apakah jam tangan saya terlihat bagus?",
  "Chinese_tw": "我的手錶好看嗎",
  "Malay": "Adakah jam tangan saya kelihatan baik?",
  "Vietnamese": "Đồng hồ của tôi có đẹp không?",
  "Japanese": "私の時計は素敵ですか？",
  "Korean": "내 시계 예쁘니?",
  "Russian": "Мои часы красивые?",
  "Hindi": "क्या मेरी घड़ी अच्छी लगती है?",
  "Portuguese": "Meu relógio está bonito?",
  "Spanish": "¿Mi reloj se ve bien?",
  "German": "Sieht meine Uhr gut aus?",
  "French": "Ma montre est-elle jolie ?",
  "Arabic": "هل ساعتي جميلة؟"
},
  "18": {
  "id": "18",
  "Chinese": "送你玫瑰",
  "English": "Here are roses for you",
  "Thailand": "นี่คือกุหลาบสำหรับคุณ",
  "Indonasia": "Ini bunga mawar untukmu",
  "Chinese_tw": "送你玫瑰",
  "Malay": "Ini adalah bunga mawar untukmu",
  "Vietnamese": "Tặng bạn hoa hồng",
  "Japanese": "あなたにバラを贈ります",
  "Korean": "너에게 장미를 줄게",
  "Russian": "Дарю тебе розы",
  "Hindi": "तुम्हें गुलाब देता हूँ",
  "Portuguese": "Te dou rosas",
  "Spanish": "Te regalo rosas",
  "German": "Ich schenke dir Rosen",
  "French": "Je t'offre des roses",
  "Arabic": "أهديك الورود"
},
  "19": {
  "id": "19",
  "Chinese": "今晚月色真美",
  "English": "The moonlight is really beautiful tonight",
  "Thailand": "คืนนี้แสงจันทร์สวยจริงๆ",
  "Indonasia": "Bulan malam ini sangat indah",
  "Chinese_tw": "今晚月色真美",
  "Malay": "Cahaya bulan malam ini sangat indah",
  "Vietnamese": "Đêm nay trăng thật đẹp",
  "Japanese": "今夜の月は本当に美しい",
  "Korean": "오늘 밤 달빛이 정말 아름다워",
  "Russian": "Сегодня ночью лунный свет действительно красив",
  "Hindi": "आज रात चाँदनी सच में खूबसूरत है",
  "Portuguese": "A lua esta linda esta noite",
  "Spanish": "Esta noche la luna se ve hermosa",
  "German": "Der Mondschein ist heute Nacht wirklich schön",
  "French": "La lune est vraiment belle ce soir",
  "Arabic": "الليل القمر جميل حقاً"
},
  "20": {
  "id": "20",
  "Chinese": "糟了，满月到了我要暴露了",
  "English": "Oh no, the full moon is here and I will be exposed",
  "Thailand": "โอ้ไม่, พระจันทร์เต็มดวงมาแล้วและฉันจะถูกเปิดเผย",
  "Indonasia": "Oh tidak, bulan purnama sudah tiba dan saya akan terungkap",
  "Chinese_tw": "糟了，滿月到了我要暴露了",
  "Malay": "Oh tidak, bulan purnama sudah tiba dan saya akan terdedah",
  "Vietnamese": "Chết tiệt, trăng tròn đến rồi tôi sẽ bị lộ.",
  "Japanese": "やばい、満月が来たら暴露される。",
  "Korean": "큰일이다, 보름달이 왔으니 드러날 거야.",
  "Russian": "Черт, полнолуние пришло, я буду раскрыт.",
  "Hindi": "बुरा हुआ, पूर्णिमा आ गई है, मैं उजागर हो जाऊंगा।",
  "Portuguese": "Droga, a lua cheia chegou e eu vou ser exposto",
  "Spanish": "Maldita sea, llegó la luna llena y voy a ser expuesto",
  "German": "Verdammtes, der Vollmond ist da und ich werde entlarvt",
  "French": "Mince, la pleine lune est arrivée et je vais être exposé",
  "Arabic": "يا إلهي، لقد حان وقت البدر وسأتعرض للكشف"
},
  "21": {
  "id": "21",
  "Chinese": "让我进去不然吃了你",
  "English": "Let me in or I'll eat you",
  "Thailand": "ให้ฉันเข้าไปไม่งั้นฉันจะกินคุณ",
  "Indonasia": "Biarkan saya masuk atau saya akan memakanmu",
  "Chinese_tw": "讓我進去不然吃了你",
  "Malay": "Biarkan saya masuk atau saya akan makan anda",
  "Vietnamese": "Để tôi vào không thì tôi sẽ ăn bạn.",
  "Japanese": "入れてくれなければ食べちゃうぞ。",
  "Korean": "나를 들어가게 해주지 않으면 너를 먹을 거야.",
  "Russian": "Пусти меня внутрь, иначе я тебя съем.",
  "Hindi": "मुझे अंदर आने दो वरना मैं तुम्हें खा जाऊंगा।",
  "Portuguese": "Deixe-me entrar ou eu vou te comer",
  "Spanish": "Déjame entrar o te comeré",
  "German": "Lass mich rein oder ich esse dich",
  "French": "Laisse-moi entrer sinon je te mange",
  "Arabic": "دعني أدخل أو سأأكلك"
},
  "22": {
  "id": "22",
  "Chinese": "算你识相",
  "English": "Glad you know what’s good for you.",
  "Thailand": "ถือว่าเธอรู้จักเจียมตัว",
  "Indonasia": "Bagus, kamu tahu diri.",
  "Chinese_tw": "算你識相",
  "Malay": "Bagus, kamu tahu apa yang baik untukmu.",
  "Vietnamese": "Xem ra bạn cũng biết điều.",
  "Japanese": "分かればいいんだよ。",
  "Korean": "알아들었네.",
  "Russian": "Ну ладно, понял, что к чему.",
  "Hindi": "चलो, समझदारी दिखा दी।",
  "Portuguese": "Ainda bem que você sabe se comportar.",
  "Spanish": "Veo que sabes comportarte.",
  "German": "Na gut, wenigstens weißt du, was sich gehört.",
  "French": "Content que tu sois raisonnable.",
  "Arabic": "حسنًا، يبدو أنك تفهمت الأمر."
},
  "23": {
  "id": "23",
  "Chinese": "我最怕火了",
  "English": "I'm most afraid of fire",
  "Thailand": "ฉันกลัวไฟมากที่สุด",
  "Indonasia": "Saya paling takut pada api",
  "Chinese_tw": "我最怕火了",
  "Malay": "Saya paling takut kepada api",
  "Vietnamese": "Tôi sợ lửa nhất.",
  "Japanese": "火が一番怖い。",
  "Korean": "나는 불이 제일 무서워.",
  "Russian": "Я больше всего боюсь огня.",
  "Hindi": "मुझे आग से सबसे ज्यादा डर लगता है।",
  "Portuguese": "Eu tenho medo de fogo",
  "Spanish": "Tengo miedo del fuego",
  "German": "Ich habe Angst vor Feuer",
  "French": "J'ai peur du feu",
  "Arabic": "أخاف من النار"
},
  "24": {
  "id": "24",
  "Chinese": "你昨晚干得不错",
  "English": "You did well last night",
  "Thailand": "คุณทำได้ดีเมื่อคืนนี้",
  "Indonasia": "Kamu melakukan dengan baik semalam",
  "Chinese_tw": "你昨晚幹得不錯",
  "Malay": "Anda lakukan dengan baik malam tadi",
  "Vietnamese": "Tối qua bạn làm tốt lắm.",
  "Japanese": "昨晩はよくやった。",
  "Korean": "어젯밤 잘했어.",
  "Russian": "Ты вчера неплохо справился.",
  "Hindi": "तुमने कल रात अच्छा किया।",
  "Portuguese": "Você se saiu bem ontem à noite",
  "Spanish": "Lo hiciste bien anoche",
  "German": "Du hast es letzte Nacht gut gemacht",
  "French": "Tu as bien travaillé hier soir",
  "Arabic": "لقد قمت بعمل جيد الليلة الماضية"
},
  "25": {
  "id": "25",
  "Chinese": "昨晚我们被举报了",
  "English": "We were reported last night",
  "Thailand": "เราถูกแจ้งเมื่อคืนที่ผ่านมา",
  "Indonasia": "Kami dilaporkan semalam",
  "Chinese_tw": "昨晚我們被舉報了",
  "Malay": "Kami telah dilaporkan malam tadi",
  "Vietnamese": "Tối qua chúng tôi đã bị báo cáo.",
  "Japanese": "昨晩私たちは通報された。",
  "Korean": "어젯밤 우리는 신고당했어.",
  "Russian": "Вчера нас сообщили.",
  "Hindi": "कल रात हमें रिपोर्ट किया गया।",
  "Portuguese": "Fomos denunciados ontem à noite",
  "Spanish": "Nos denunciaron anoche",
  "German": "Wir wurden letzte Nacht angezeigt",
  "French": "Nous avons été dénoncés hier soir",
  "Arabic": "لقد تم الإبلاغ عنا الليلة الماضية"
},
  "26": {
  "id": "26",
  "Chinese": "你居然敢拒绝我",
  "English": "How dare you refuse me?",
  "Thailand": "เธอกล้าปฏิเสธฉันได้ยังไง",
  "Indonasia": "Beraninya kamu menolak aku?",
  "Chinese_tw": "你居然敢拒絕我",
  "Malay": "Beranikah kamu menolak saya?",
  "Vietnamese": "Bạn dám từ chối tôi sao?",
  "Japanese": "よくも私を断るなんて！",
  "Korean": "네가 감히 나를 거절해?",
  "Russian": "Как ты смеешь меня отвергать?",
  "Hindi": "तुमने मेरी बात मानने की हिम्मत कैसे की?",
  "Portuguese": "Como você ousa me recusar?",
  "Spanish": "¿Cómo te atreves a rechazarme?",
  "German": "Wie kannst du es wagen, mich abzulehnen?",
  "French": "Comment oses-tu me refuser ?",
  "Arabic": "كيف تجرؤ على رفضي؟"
},
  "1000": {
  "id": "1000",
  "Chinese": "识别怪物，阻止他们进入",
  "English": "Identify the monsters and stop them from entering",
  "Thailand": "ระบุปีศาจและหยุดพวกเขาจากการเข้า",
  "Indonasia": "Identifikasi monster dan hentikan mereka masuk",
  "Chinese_tw": "識別怪物，阻止他們進入",
  "Malay": "Kenal pasti raksasa dan halang mereka daripada masuk",
  "Vietnamese": "Nhận diện quái vật, ngăn chặn chúng vào.",
  "Japanese": "モンスターを識別し、彼らの侵入を阻止する。",
  "Korean": "괴물을 인식하고 그들이 들어오는 것을 막아라.",
  "Russian": "Опознайте монстров, остановите их вход.",
  "Hindi": "राक्षसों की पहचान करो, उन्हें अंदर आने से रोकें।",
  "Portuguese": "Identifique os monstros, impeça-os de entrar",
  "Spanish": "Identifica a los monstruos, impídeles entrar",
  "German": "Erkenne die Monster, verhindere, dass sie eintreten",
  "French": "Identifie les monstres, empêche-les d'entrer",
  "Arabic": "حدد الوحوش، ومنعهم من الدخول"
},
  "2000": {
  "id": "2000",
  "Chinese": "第二天",
  "English": "The next day",
  "Thailand": "วันถัดไป",
  "Indonasia": "Hari berikutnya",
  "Chinese_tw": "第二天",
  "Malay": "Hari berikutnya",
  "Vietnamese": "Ngày hôm sau",
  "Japanese": "次の日",
  "Korean": "다음 날",
  "Russian": "на следующий день",
  "Hindi": "अगले दिन",
  "Portuguese": "No dia seguinte",
  "Spanish": "Al día siguiente",
  "German": "Am nächsten Tag",
  "French": "Le lendemain",
  "Arabic": "اليوم التالي"
},
  "2001": {
  "id": "2001",
  "Chinese": "禁止通行",
  "English": "No Entry",
  "Thailand": "ห้ามผ่าน",
  "Indonasia": "Dilarang Lewat",
  "Chinese_tw": "禁止通過",
  "Malay": "Dilarang Masuk",
  "Vietnamese": "Cấm Qua",
  "Japanese": "通行禁止",
  "Korean": "통행 금지",
  "Russian": "Вход Запрещён",
  "Hindi": "प्रवेश वर्जित",
  "Portuguese": "Proibido Passar",
  "Spanish": "Prohibido Paso",
  "German": "Durchgang Verboten",
  "French": "Passage Interdit",
  "Arabic": "ممنوع المرور"
},
  "2002": {
  "id": "2002",
  "Chinese": "允许通行",
  "English": "Allow",
  "Thailand": "อนุญาต",
  "Indonasia": "Izinkan",
  "Chinese_tw": "允許通過",
  "Malay": "Benarkan",
  "Vietnamese": "Cho phép",
  "Japanese": "許可",
  "Korean": "허용",
  "Russian": "Разрешено",
  "Hindi": "अनुमति",
  "Portuguese": "Permitir",
  "Spanish": "Permitir",
  "German": "Erlaubt",
  "French": "Permis",
  "Arabic": "مسموح"
}
}