{
"skeleton": {
	"hash": "MCjKUF9e7RNAxdeuF5qKp7MeVBA",
	"spine": "3.8.99",
	"x": -517.26,
	"y": -300.12,
	"width": 1057.52,
	"height": 986.94,
	"images": "./Image/",
	"audio": ""
},
"bones": [
	{ "name": "root" },
	{ "name": "branches", "parent": "root", "length": 877.52, "rotation": 85.57, "x": -272.55, "y": -191.11 },
	{ "name": "branches2", "parent": "branches", "x": 746.29, "y": 0.99, "color": "13ff00ff" },
	{ "name": "branches3", "parent": "root", "length": 877.52, "rotation": 77.1, "x": -508, "y": -181.18 },
	{ "name": "branches4", "parent": "branches3", "x": 748.89, "y": 0.99, "color": "13ff00ff" },
	{
		"name": "branches5",
		"parent": "root",
		"length": 877.52,
		"rotation": 95.68,
		"x": 511.33,
		"y": -186.76,
		"scaleY": -1
	},
	{ "name": "branches6", "parent": "branches5", "x": 736.88, "y": 0.99, "color": "13ff00ff" },
	{ "name": "zhangpeng", "parent": "root", "x": 144.82, "y": 271.39, "color": "ff0000ff" },
	{ "name": "Women-1", "parent": "root", "x": 312.56, "y": -320.33 },
	{ "name": "Women-2", "parent": "Women-1", "x": -0.8, "y": 210.4 },
	{ "name": "Women-3", "parent": "Women-2", "length": 98.41, "rotation": 107.99 },
	{ "name": "Women-4", "parent": "Women-3", "length": 74.21, "rotation": -6.8, "x": 98.41 },
	{ "name": "Women-5", "parent": "Women-4", "length": 113.21, "rotation": 9.94, "x": 74.21 },
	{ "name": "Women-6", "parent": "Women-4", "length": 93.79, "rotation": -92.85, "x": 46.54, "y": -45.09 },
	{ "name": "Women-7", "parent": "Women-6", "length": 75.61, "rotation": 21.48, "x": 93.79 },
	{
		"name": "Women-8",
		"parent": "branches5",
		"length": 37.29,
		"rotation": -76.93,
		"x": 278.28,
		"y": -8.86,
		"scaleX": -1,
		"color": "ff3f00ff"
	},
	{ "name": "Women-9", "parent": "Women-4", "length": 92.88, "rotation": 157.89, "x": 41.96, "y": 39 },
	{ "name": "Women-10", "parent": "Women-9", "length": 80.45, "rotation": -37.3, "x": 92.88 },
	{ "name": "Women-11", "parent": "Women-10", "length": 54.35, "rotation": 0.84, "x": 80.45 },
	{ "name": "Women-12", "parent": "Women-2", "length": 138.93, "rotation": -141.55, "x": 40.8, "y": -21.6 },
	{ "name": "Women-13", "parent": "Women-12", "length": 156.81, "rotation": 140.96, "x": 138.93 },
	{
		"name": "Women-14",
		"parent": "Women-1",
		"length": 77.42,
		"rotation": -66.88,
		"x": 88,
		"y": 100.8,
		"color": "ff3f00ff"
	},
	{ "name": "Women-2(1)", "parent": "Women-4", "length": 114.03, "rotation": 167.1, "x": 23.24, "y": -60.55 },
	{ "name": "Women-2(1)2", "parent": "Women-2(1)", "length": 126.93, "rotation": -67.71, "x": 114.03 }
],
"slots": [
	{ "name": "cankao", "bone": "root" },
	{ "name": "Women-1", "bone": "Women-1", "attachment": "Women-1" },
	{ "name": "branches", "bone": "branches", "attachment": "branches" },
	{ "name": "branches2", "bone": "branches3", "attachment": "branches" },
	{ "name": "branches3", "bone": "branches5", "attachment": "branches" },
	{ "name": "cloth", "bone": "root", "attachment": "cloth" },
	{ "name": "Women-2", "bone": "root" },
	{ "name": "Women-2(1)", "bone": "Women-2(1)" }
],
"ik": [
	{
		"name": "Women-8",
		"bones": [ "Women-6", "Women-7" ],
		"target": "Women-8"
	},
	{
		"name": "Women-14",
		"order": 1,
		"bones": [ "Women-12", "Women-13" ],
		"target": "Women-14"
	}
],
"skins": [
	{
		"name": "default",
		"attachments": {
			"Women-1": {
				"Women-1": {
					"type": "mesh",
					"uvs": [ 0.5437, 0.22858, 0.57916, 0.13919, 0.50198, 0.06053, 0.4269, 0, 0.28089, 0.01047, 0.15574, 0.07483, 0.19537, 0.21428, 0.25586, 0.31618, 0.22666, 0.44133, 0.22666, 0.4896, 0.19329, 0.51284, 0.10986, 0.60938, 0, 0.64514, 0, 0.75777, 0.14114, 0.71308, 0.16617, 0.65587, 0.31218, 0.5486, 0.33512, 0.50212, 0.35598, 0.56648, 0.21415, 0.68984, 0.19955, 0.75956, 0.2496, 0.8865, 0.37267, 0.9008, 0.64382, 0.89901, 0.68553, 0.90795, 0.70848, 0.93298, 0.72516, 1, 0.82945, 1, 0.81902, 0.8132, 0.77105, 0.7542, 0.68553, 0.7542, 0.76271, 0.68626, 0.73142, 0.57184, 0.62296, 0.45206, 0.58959, 0.36624, 0.71891, 0.31976, 0.75645, 0.31797, 0.78565, 0.29294, 0.8962, 0.22679, 0.91814, 0.22112, 1, 0.19997, 1, 0.0784, 0.94417, 0.07483, 0.86908, 0.15349, 0.8567, 0.17076, 0.7208, 0.21997, 0.69971, 0.229, 0.57201, 0.21997 ],
					"triangles": [ 12, 11, 14, 13, 12, 14, 15, 11, 10, 10, 9, 16, 15, 10, 16, 14, 11, 15, 9, 8, 17, 7, 17, 8, 7, 34, 17, 16, 9, 17, 42, 41, 40, 43, 42, 40, 39, 43, 40, 44, 43, 39, 38, 44, 39, 37, 45, 44, 37, 44, 38, 37, 46, 45, 37, 35, 46, 36, 35, 37, 35, 34, 47, 35, 47, 46, 0, 47, 34, 7, 0, 34, 28, 24, 30, 28, 30, 29, 25, 24, 28, 27, 26, 25, 27, 25, 28, 21, 20, 22, 18, 30, 22, 23, 22, 30, 23, 30, 24, 30, 32, 31, 30, 18, 32, 19, 22, 20, 18, 22, 19, 34, 33, 17, 18, 17, 33, 32, 18, 33, 6, 5, 4, 1, 0, 2, 6, 0, 7, 4, 3, 2, 2, 6, 4, 0, 6, 2 ],
					"vertices": [ 3, 12, -12.48, -61.74, 0.21049, 11, 72.57, -62.96, 0.00573, 13, 16.56, 26.89, 0.78378, 2, 12, 22, -90.57, 0.63111, 13, 37.04, 66.89, 0.36889, 2, 12, 68.27, -74.69, 0.8355, 13, 11.32, 108.51, 0.1645, 2, 12, 106.19, -56.5, 0.9495, 13, -14.82, 141.46, 0.0505, 2, 12, 123.01, 0.87, 0.99997, 16, -148.36, -42.01, 3.0E-5, 2, 12, 112.83, 59.54, 0.96858, 16, -108.6, -86.34, 0.03142, 2, 12, 45.09, 68.38, 0.74963, 16, -46.49, -57.89, 0.25037, 2, 12, -9.05, 62.84, 0.14579, 16, -3.54, -24.47, 0.85421, 2, 16, 57.21, -24.88, 0.99579, 17, -13.3, -41.41, 0.00421, 2, 16, 79.77, -20.52, 0.69187, 17, 2.01, -24.27, 0.30813, 2, 16, 93.21, -31.8, 0.16827, 17, 19.53, -25.09, 0.83173, 2, 17, 75.53, -13.5, 0.71799, 18, -5.12, -13.42, 0.28201, 1, 18, 39.39, -31.25, 1, 1, 18, 75.69, 8.21, 1, 2, 17, 98.9, 31.82, 0.053, 18, 18.91, 31.54, 0.947, 2, 17, 73.14, 18.31, 0.73212, 18, -7.05, 18.42, 0.26788, 3, 10, 47.31, 65.78, 0.02532, 16, 100.73, 19.06, 0.47484, 17, -5.3, 19.92, 0.49984, 5, 11, -38.65, 45.78, 9.0E-5, 10, 65.46, 50.04, 0.33097, 19, 42.52, -121.11, 0.00601, 16, 77.24, 24.06, 0.65777, 17, -27.03, 9.65, 0.00516, 3, 10, 33.7, 51.41, 0.6973, 19, 54.9, -91.83, 0.16472, 16, 105.7, 38.22, 0.13798, 4, 10, -4.27, 124.59, 0.15608, 19, 136.74, -81.83, 0.83766, 20, -49.84, 64.95, 3.3E-4, 16, 174.32, -7.48, 0.00593, 4, 10, -34, 140.5, 0.07546, 19, 162.04, -59.55, 0.87743, 20, -55.46, 31.7, 0.04552, 16, 208.04, -7.04, 0.00159, 3, 10, -97.77, 139.74, 4.5E-4, 19, 183.62, 0.47, 0.39041, 20, -34.42, -28.51, 0.60914, 1, 20, 15.86, -34.81, 1, 2, 20, 126.48, -32.83, 0.77555, 21, 17.86, -40.97, 0.22445, 2, 20, 143.54, -36.91, 0.35101, 21, 28.46, -26.99, 0.64899, 2, 20, 153.02, -48.73, 0.08015, 21, 43.09, -23.06, 0.91985, 1, 21, 75.11, -29.32, 1, 1, 21, 91.81, 9.81, 1, 2, 20, 197.54, 8.75, 0.10295, 21, 8.37, 40.81, 0.89705, 3, 19, -22.15, 83.46, 0.03004, 20, 177.68, 36.63, 0.51495, 21, -25.15, 33.84, 0.455, 3, 19, 5.18, 61.76, 0.34777, 20, 142.79, 36.27, 0.62875, 21, -38.85, 1.75, 0.02348, 3, 10, -71.79, -88.81, 3.3E-4, 19, -39.59, 56.02, 0.8057, 20, 173.95, 68.93, 0.19397, 4, 10, -16.05, -93.49, 0.16346, 19, -63.46, 5.43, 0.80661, 20, 160.63, 123.26, 0.0247, 13, 68.65, -145.88, 0.00522, 4, 11, -38.06, -74.05, 0.005, 10, 51.85, -69.02, 0.69353, 19, -64.27, -66.74, 0.15544, 13, 33.13, -83.05, 0.14602, 4, 11, 4.66, -68.62, 0.05175, 10, 94.91, -68.68, 0.27488, 19, -79.01, -107.2, 0.01107, 13, 25.58, -40.66, 0.6623, 3, 10, 99.65, -125.7, 0.00126, 13, 81, -26.42, 0.91676, 14, -21.58, -19.9, 0.08198, 2, 13, 96.27, -27.8, 0.6353, 14, -7.87, -26.77, 0.3647, 2, 13, 109.79, -17.74, 0.20253, 14, 8.39, -22.36, 0.79747, 2, 14, 63.18, -17.47, 0.86075, 15, -10.17, -18.88, 0.13925, 2, 14, 72.29, -19.58, 0.52036, 15, -0.87, -19.84, 0.47964, 1, 15, 33.82, -23.46, 1, 1, 15, 56.17, 29.92, 1, 1, 15, 35.81, 40.29, 1, 2, 14, 70.93, 18.3, 0.56951, 15, -6.91, 17.58, 0.43049, 2, 14, 62.46, 13.68, 0.87964, 15, -14.74, 11.95, 0.12036, 2, 13, 88.65, 20.47, 0.5459, 14, 2.71, 20.93, 0.4541, 2, 13, 79.51, 17.46, 0.82588, 14, -6.89, 21.48, 0.17412, 2, 12, -12.82, -73.99, 0.08231, 13, 28.58, 29.27, 0.91769 ],
					"hull": 48,
					"edges": [ 0, 2, 2, 4, 4, 6, 6, 8, 8, 10, 10, 12, 12, 14, 14, 16, 16, 18, 18, 20, 20, 22, 22, 24, 24, 26, 26, 28, 28, 30, 30, 32, 32, 34, 34, 36, 36, 38, 38, 40, 40, 42, 42, 44, 44, 46, 46, 48, 48, 50, 50, 52, 52, 54, 54, 56, 56, 58, 58, 60, 60, 62, 62, 64, 64, 66, 66, 68, 68, 70, 70, 72, 72, 74, 74, 76, 80, 82, 82, 84, 84, 86, 86, 88, 88, 90, 90, 92, 92, 94, 0, 94, 76, 78, 78, 80 ],
					"width": 408,
					"height": 476
				},
				"Women-2": {
					"type": "mesh",
					"uvs": [ 0.65168, 0.21777, 0.68799, 0.14595, 0.59521, 0.06466, 0.4762, 0, 0.35921, 0, 0.22004, 0.07414, 0.20793, 0.13782, 0.1918, 0.1988, 0.28458, 0.30313, 0.20995, 0.41559, 0.19583, 0.44811, 0.17163, 0.47386, 0, 0.62155, 0, 0.71233, 0.13734, 0.69336, 0.18978, 0.64187, 0.32089, 0.57954, 0.35921, 0.53347, 0.38947, 0.5958, 0.23012, 0.68387, 0.20995, 0.75162, 0.2866, 0.88847, 0.45401, 0.88712, 0.75657, 0.88847, 0.79086, 0.90338, 0.8312, 1, 1, 1, 1, 0.77872, 0.87356, 0.71504, 0.91793, 0.62426, 0.89373, 0.55651, 0.7122, 0.30448, 0.69808, 0.22725, 0.61493, 0.47574 ],
					"triangles": [ 0, 2, 1, 4, 6, 5, 6, 0, 8, 7, 6, 8, 4, 3, 2, 2, 6, 4, 0, 6, 2, 31, 33, 8, 0, 31, 8, 31, 0, 32, 17, 9, 8, 33, 17, 8, 10, 9, 17, 11, 10, 17, 33, 31, 30, 16, 11, 17, 18, 17, 33, 15, 12, 11, 16, 15, 11, 14, 12, 15, 13, 12, 14, 28, 33, 30, 28, 30, 29, 18, 33, 28, 22, 18, 28, 19, 18, 22, 20, 19, 22, 21, 20, 22, 23, 22, 28, 24, 23, 28, 27, 24, 28, 26, 25, 24, 26, 24, 27 ],
					"vertices": [ 4, 12, -3.05, -76.11, 0.47637, 11, 84.34, -75.49, 0.48168, 10, 173.22, -84.96, 0.03937, 19, -121.63, -174.88, 0.00258, 3, 12, 27.45, -101.59, 0.79716, 11, 118.78, -95.33, 0.20149, 10, 205.06, -108.73, 0.00135, 2, 12, 78.96, -86.48, 0.95292, 11, 166.9, -71.56, 0.04708, 2, 12, 125.66, -59.62, 0.99981, 11, 208.27, -37.04, 1.9E-4, 1, 12, 140.5, -21.2, 1, 2, 12, 121.92, 38.5, 0.99143, 16, -127.46, -73.33, 0.00857, 2, 12, 92.32, 54.5, 0.94747, 16, -93.89, -71.19, 0.05253, 2, 12, 64.57, 71.31, 0.8621, 16, -61.44, -70.71, 0.1379, 3, 12, 1.8, 60.55, 0.26892, 11, 65.54, 59.95, 0.00673, 16, -13.95, -28.28, 0.72435, 2, 16, 48.89, -42.91, 0.88889, 17, -8.99, -60.79, 0.11111, 2, 16, 66.56, -44.56, 0.68984, 17, 6.07, -51.4, 0.31016, 3, 16, 81.42, -50.37, 0.418, 17, 21.41, -47.01, 0.58199, 18, -59.73, -46.14, 1.0E-5, 2, 17, 118.02, -29.55, 0.00578, 18, 37.13, -30.09, 0.99422, 1, 18, 69.34, 4.91, 1, 2, 17, 107.04, 30.72, 0.01042, 18, 27.03, 30.33, 0.98958, 2, 17, 75.3, 22.9, 0.62888, 18, -4.82, 22.97, 0.37112, 4, 10, 28.89, 84.35, 0.00924, 19, 87.45, -98.84, 4.3E-4, 16, 125.84, 11.71, 0.00469, 17, 19.12, 29.29, 0.98563, 4, 10, 47.68, 64.06, 0.24914, 19, 61.87, -109.35, 0.02459, 16, 99.58, 20.38, 0.44008, 17, -7.02, 20.27, 0.28619, 4, 10, 13.33, 64.02, 0.48299, 19, 73.84, -77.15, 0.35501, 16, 129.63, 37.03, 0.14398, 17, 6.79, 51.73, 0.01802, 4, 10, -13.24, 131.62, 0.07383, 19, 146.47, -75.89, 0.91132, 20, -53.65, 54.2, 0.00234, 16, 185.58, -9.3, 0.01251, 4, 10, -44.81, 149.34, 0.02622, 19, 174.1, -52.51, 0.87012, 20, -60.39, 18.63, 0.09971, 16, 221.78, -9.55, 0.00394, 2, 19, 197.57, 20.43, 0.10144, 20, -32.68, -52.8, 0.89856, 1, 20, 26.24, -51.49, 1, 2, 20, 132.74, -51.11, 0.45416, 21, 37.12, -42.58, 0.54584, 2, 20, 144.89, -58.8, 0.17, 21, 49.04, -34.55, 0.83, 1, 21, 101.18, -41.37, 1, 1, 21, 124.51, 13.27, 1, 3, 19, -34.85, 131.55, 0.00297, 20, 217.84, 7.27, 0.01168, 21, 17.88, 58.8, 0.98535, 3, 19, -20.74, 77.74, 0.32252, 20, 172.99, 40.19, 0.47703, 21, -30.29, 30.97, 0.20046, 5, 11, -142.79, -126.1, 0.00356, 10, -58.32, -108.3, 0.02872, 19, -62.56, 50.21, 0.74621, 20, 188.13, 87.91, 0.21994, 21, -67.9, 64.02, 0.00156, 4, 11, -106.32, -124.63, 0.02243, 10, -21.92, -111.16, 0.14207, 19, -77.96, 17.11, 0.74255, 20, 179.24, 123.32, 0.09295, 4, 12, -53.11, -79.6, 0.09702, 11, 35.63, -87.57, 0.64528, 10, 123.42, -91.18, 0.22553, 19, -110.05, -126.05, 0.03216, 4, 12, -13.57, -89.55, 0.32591, 11, 76.3, -90.55, 0.5959, 10, 163.45, -98.95, 0.07237, 19, -131.33, -160.83, 0.00582, 3, 11, -45.76, -36.57, 0.08705, 10, 48.65, -30.89, 0.82386, 19, -27.43, -77.07, 0.08909 ],
					"hull": 33,
					"edges": [ 0, 2, 2, 4, 4, 6, 6, 8, 8, 10, 10, 12, 12, 14, 14, 16, 16, 18, 18, 20, 20, 22, 22, 24, 24, 26, 26, 28, 28, 30, 30, 32, 32, 34, 34, 36, 36, 38, 38, 40, 40, 42, 42, 44, 44, 46, 46, 48, 48, 50, 50, 52, 52, 54, 54, 56, 56, 58, 58, 60, 60, 62, 62, 64, 0, 64 ],
					"width": 352,
					"height": 524
				}
			},
			"Women-2(1)": {
				"Women-2(1)": {
					"type": "mesh",
					"uvs": [ 0.65079, 0, 0.56829, 0.11301, 0.58876, 0.29137, 0.61734, 0.54051, 0.59728, 0.58326, 0.54154, 0.60701, 0.0265, 0.71389, 0.05772, 1, 0.45681, 1, 0.68869, 1, 0.88489, 0.83026, 0.95401, 0.75189, 1, 0.63076, 1, 0.31489, 1, 0.16526, 0.9005, 0 ],
					"triangles": [ 8, 5, 9, 5, 4, 9, 9, 4, 10, 5, 8, 6, 8, 7, 6, 4, 3, 10, 10, 3, 13, 12, 11, 10, 2, 0, 13, 13, 12, 10, 0, 14, 13, 13, 3, 2, 0, 15, 14, 2, 1, 0 ],
					"vertices": [ 1, 22, -9.25, -33.26, 1, 1, 22, 12.02, -48.8, 1, 2, 22, 44.7, -43.82, 0.99515, 23, 14.25, -80.76, 0.00485, 2, 22, 90.36, -36.85, 0.58994, 23, 25.12, -35.88, 0.41006, 2, 22, 98.34, -40.55, 0.31549, 23, 31.57, -29.9, 0.68451, 2, 22, 103.03, -51.34, 0.10262, 23, 43.33, -29.65, 0.89738, 1, 23, 144.75, -46.72, 1, 1, 23, 157.53, 4.71, 1, 1, 23, 84.3, 32.21, 1, 1, 23, 41.75, 48.19, 1, 2, 22, 142.09, 17.15, 0.08874, 23, -5.23, 32.47, 0.91126, 2, 22, 127.27, 30.26, 0.45062, 23, -22.98, 23.73, 0.54938, 2, 22, 104.72, 38.61, 0.86999, 23, -39.25, 6.03, 0.13001, 1, 22, 46.63, 36.88, 1, 1, 22, 19.11, 36.06, 1, 1, 22, -10.71, 15.66, 1 ],
					"hull": 16,
					"edges": [ 0, 2, 6, 8, 8, 10, 10, 12, 12, 14, 14, 16, 16, 18, 18, 20, 20, 22, 22, 24, 28, 30, 0, 30, 24, 26, 26, 28, 2, 4, 4, 6 ],
					"width": 196,
					"height": 184
				}
			},
			"branches": {
				"branches": { "x": 438.33, "y": -8.15, "rotation": -84.12, "width": 124, "height": 876 }
			},
			"branches2": {
				"branches": { "x": 438.33, "y": -8.15, "rotation": -84.12, "width": 124, "height": 876 }
			},
			"branches3": {
				"branches": { "x": 438.33, "y": -8.15, "rotation": -84.12, "width": 124, "height": 876 }
			},
			"cloth": {
				"cloth": {
					"type": "mesh",
					"uvs": [ 0, 0.0739, 0.02617, 0.04752, 0.046, 0.06599, 0.19832, 0.1829, 0.21139, 0.12465, 0.21668, 0.10031, 0.24904, 0.08726, 0.25588, 0.09683, 0.38049, 0.19037, 0.46344, 0.22564, 0.58966, 0.23068, 0.69515, 0.21809, 0.83309, 0.16014, 0.94399, 0.08204, 1, 0.02311, 1, 0.28435, 0.98158, 0.50716, 0.96967, 0.61217, 0.94492, 0.62626, 0.7621, 0.76231, 0.67705, 1, 0.5639, 1, 0.53653, 0.91938, 0.46332, 0.80778, 0.34724, 0.76821, 0.20255, 0.7011, 0.09568, 0.62392, 0.03684, 0.55345, 0, 0.36387, 0, 0.22629, 0.24834, 0.21138, 0.37526, 0.26205, 0.4703, 0.27952, 0.59097, 0.2638, 0.55159, 0.73986, 0.65462, 0.72582, 0.76519, 0.6714, 0.61819, 0.82413, 0.68038, 0.80482, 0.55222, 0.83115 ],
					"triangles": [ 16, 12, 15, 13, 14, 15, 20, 38, 19, 21, 37, 20, 20, 37, 38, 22, 39, 21, 21, 39, 37, 22, 23, 39, 23, 34, 39, 39, 34, 37, 37, 35, 38, 37, 34, 35, 19, 38, 36, 36, 38, 35, 34, 33, 35, 34, 32, 33, 35, 11, 36, 35, 33, 11, 33, 10, 11, 19, 36, 18, 36, 12, 18, 36, 11, 12, 17, 18, 16, 16, 18, 12, 15, 12, 13, 23, 32, 34, 32, 10, 33, 25, 30, 24, 24, 31, 23, 32, 31, 9, 31, 8, 9, 31, 30, 8, 3, 4, 30, 4, 5, 30, 30, 7, 8, 30, 6, 7, 30, 5, 6, 24, 30, 31, 25, 3, 30, 23, 31, 32, 26, 3, 25, 32, 9, 10, 26, 27, 3, 3, 28, 2, 3, 27, 28, 2, 29, 1, 2, 28, 29, 29, 0, 1 ],
					"vertices": [ 1, 4, 8.51, 19.24, 1, 2, 4, 23.63, -4.19, 0.99426, 2, 20.95, 192.04, 0.00574, 2, 4, 21.5, -24.38, 0.95705, 2, 15.86, 172.38, 0.04295, 2, 4, 12.32, -167.23, 0.15577, 2, -14.27, 32.44, 0.84423, 1, 2, 7.65, 24.08, 1, 1, 2, 16.8, 19.45, 1, 2, 2, 24, -13.05, 0.97976, 7, -392.85, 304.54, 0.02024, 2, 2, 21.09, -20.32, 0.97279, 7, -385.82, 301.09, 0.02721, 1, 2, -2.8, -147.36, 1, 3, 2, -9.02, -231.7, 0.99131, 6, 26.36, -471.65, 3.2E-4, 7, -177.39, 254.75, 0.00837, 3, 2, -1.02, -374.45, 0.19401, 6, 9.18, -329.72, 0.13338, 7, -34.45, 251.7, 0.6726, 3, 2, 11.69, -482.73, 0.05335, 6, 2.69, -220.89, 0.38454, 7, 74.48, 256.01, 0.56211, 3, 2, 43.21, -620.5, 0.00223, 6, 9.53, -79.73, 0.84398, 7, 214.28, 276.79, 0.15379, 2, 6, 26.46, 34.11, 0.8383, 0, 483.91, 538.13, 0.1617, 1, 0, 540.26, 559.35, 1, 1, 0, 540.26, 465.3, 1, 3, 6, -129.58, 56.6, 0.37735, 7, 363.71, 151.86, 0.0164, 0, 521.73, 385.09, 0.60625, 3, 6, -166.01, 40.93, 0.50793, 7, 351.72, 114.06, 0.03401, 0, 509.75, 347.29, 0.45805, 3, 6, -168.59, 15.66, 0.80499, 7, 326.83, 108.99, 0.07014, 0, 484.85, 342.21, 0.12487, 3, 2, -178.44, -566.07, 6.9E-4, 6, -199.12, -172.22, 0.35957, 7, 142.89, 60.01, 0.63974, 2, 6, -275.8, -265.82, 0.03242, 7, 57.35, -25.56, 0.96758, 2, 2, -279.15, -373.17, 0.03615, 7, -57.21, -25.5, 0.96385, 3, 2, -252.34, -342.15, 0.10248, 6, -232.57, -405.63, 4.0E-5, 7, -86.06, 3.62, 0.89749, 4, 4, -145.91, -487.48, 0.06369, 2, -217.97, -260.99, 0.33278, 6, -184.49, -479.5, 1.1E-4, 7, -164.33, 44.16, 0.60342, 3, 4, -158.87, -365.31, 0.12052, 2, -212.78, -138.24, 0.59313, 7, -286.31, 58.8, 0.28635, 3, 4, -167.69, -218.97, 0.40323, 2, -199.94, 7.8, 0.54553, 7, -430.92, 82.89, 0.05124, 3, 4, -163.86, -113.05, 0.707, 2, -180.54, 112, 0.28944, 7, -533.31, 110.28, 0.00356, 1, 4, -151.49, -55.44, 1, 1, 4, -93.24, -4.07, 1, 1, 4, -44.96, 6.99, 1, 2, 4, 13.33, -216.98, 0.07625, 2, -20.61, -16.92, 0.92375, 2, 4, 23.95, -344.77, 0.0387, 2, -28.94, -144.88, 0.9613, 1, 2, -27.82, -239.91, 1, 3, 2, -12.81, -376.74, 0.19134, 6, -2.83, -329.53, 0.13468, 7, -33.08, 239.77, 0.67398, 3, 2, -186.74, -351.23, 0.15415, 6, -169.58, -385.18, 0.01574, 7, -71.95, 68.33, 0.83011, 3, 2, -173.69, -456.72, 0.02725, 6, -175.25, -279.03, 0.11069, 7, 34.24, 73.19, 0.86206, 3, 2, -145.57, -566.61, 0.00221, 6, -166.86, -165.91, 0.4317, 7, 145.97, 92.74, 0.56609, 3, 2, -211.81, -422.94, 0.02543, 6, -206.85, -318.98, 0.02597, 7, -2.38, 37.79, 0.9486, 3, 2, -200.05, -485.18, 0.00578, 6, -206.2, -255.64, 0.1134, 7, 60.58, 44.71, 0.88083, 3, 2, -219.45, -355.21, 0.11334, 6, -202.49, -387, 0.00474, 7, -70.5, 35.4, 0.88192 ],
					"hull": 30,
					"edges": [ 0, 2, 2, 4, 4, 6, 6, 8, 8, 10, 10, 12, 12, 14, 14, 16, 16, 18, 18, 20, 20, 22, 22, 24, 24, 26, 26, 28, 28, 30, 30, 32, 32, 34, 34, 36, 36, 38, 38, 40, 40, 42, 42, 44, 44, 46, 46, 48, 48, 50, 50, 52, 52, 54, 54, 56, 56, 58, 0, 58, 6, 60, 60, 62, 62, 64, 64, 66, 66, 22 ],
					"width": 1006,
					"height": 360
				}
			}
		}
	}
],
"animations": {
	"Ceiling1": {
		"slots": {
			"Women-1": {
				"attachment": [
					{ "name": null }
				]
			}
		},
		"bones": {
			"branches3": {
				"rotate": [
					{ "curve": 0.25, "c3": 0.75 },
					{ "time": 0.3333, "angle": 12.62, "curve": 0.25, "c3": 0.75 },
					{ "time": 0.6667, "curve": 0.25, "c3": 0.75 },
					{ "time": 1, "angle": 12.62, "curve": 0.25, "c3": 0.75 },
					{ "time": 1.3333 }
				]
			},
			"branches": {
				"rotate": [
					{ "curve": 0.25, "c3": 0.75 },
					{ "time": 0.1667, "angle": 2.36, "curve": 0.25, "c3": 0.75 },
					{ "time": 0.3333, "curve": 0.25, "c3": 0.75 },
					{ "time": 0.5, "angle": 2.36, "curve": 0.25, "c3": 0.75 },
					{ "time": 0.6667, "curve": 0.25, "c3": 0.75 },
					{ "time": 0.8333, "angle": 2.36, "curve": 0.25, "c3": 0.75 },
					{ "time": 1, "curve": 0.25, "c3": 0.75 },
					{ "time": 1.1667, "angle": 2.36, "curve": 0.25, "c3": 0.75 },
					{ "time": 1.3333 }
				]
			},
			"branches5": {
				"rotate": [
					{ "angle": 0.32, "curve": 0.25, "c3": 0.75 },
					{ "time": 0.3333, "angle": 1.47, "curve": 0.25, "c3": 0.75 },
					{ "time": 0.6667, "angle": 0.32, "curve": 0.25, "c3": 0.75 },
					{ "time": 1, "angle": 2.32, "curve": 0.25, "c3": 0.75 },
					{ "time": 1.3333, "angle": 0.32 }
				]
			},
			"zhangpeng": {
				"translate": [
					{ "x": 137.63, "curve": 0.25, "c3": 0.625, "c4": 0.5 },
					{ "time": 0.1667, "x": 68.82, "y": -12.42, "curve": 0.375, "c2": 0.5, "c3": 0.75 },
					{ "time": 0.3333, "curve": 0.25, "c3": 0.625, "c4": 0.5 },
					{ "time": 0.5, "x": 68.82, "y": -5.52, "curve": 0.375, "c2": 0.5, "c3": 0.75 },
					{ "time": 0.6667, "x": 137.63, "curve": 0.25, "c3": 0.625, "c4": 0.5 },
					{ "time": 0.8333, "x": 68.82, "y": -11.04, "curve": 0.375, "c2": 0.5, "c3": 0.75 },
					{ "time": 1, "curve": 0.25, "c3": 0.625, "c4": 0.5 },
					{ "time": 1.1667, "x": 68.82, "y": -8.97, "curve": 0.375, "c2": 0.5, "c3": 0.75 },
					{ "time": 1.3333, "x": 137.63 }
				]
			}
		}
	},
	"Woman1": {
		"slots": {
			"branches": {
				"attachment": [
					{ "name": null }
				]
			},
			"branches2": {
				"attachment": [
					{ "name": null }
				]
			},
			"branches3": {
				"attachment": [
					{ "name": null }
				]
			},
			"cloth": {
				"attachment": [
					{ "name": null }
				]
			}
		},
		"bones": {
			"branches5": {
				"rotate": [
					{ "angle": 0.32, "curve": 0.25, "c3": 0.75 },
					{ "time": 0.3333, "angle": 1.47, "curve": 0.25, "c3": 0.75 },
					{ "time": 0.6667, "angle": 0.32, "curve": 0.25, "c3": 0.75 },
					{ "time": 1, "angle": 2.32, "curve": 0.25, "c3": 0.75 },
					{ "time": 1.3333, "angle": 0.32 }
				]
			},
			"Women-3": {
				"rotate": [
					{ "curve": 0.25, "c3": 0.75 },
					{ "time": 0.3333, "angle": 2.05, "curve": 0.25, "c3": 0.75 },
					{ "time": 0.6667, "curve": 0.25, "c3": 0.75 },
					{ "time": 1, "angle": 1.39, "curve": 0.25, "c3": 0.75 },
					{ "time": 1.3333 }
				]
			},
			"Women-4": {
				"rotate": [
					{ "angle": 0.34, "curve": 0.382, "c2": 0.58, "c3": 0.731 },
					{ "time": 0.1, "curve": 0.25, "c3": 0.75 },
					{ "time": 0.4333, "angle": 2.05, "curve": 0.25, "c3": 0.75 },
					{ "time": 0.7667, "curve": 0.25, "c3": 0.75 },
					{ "time": 1.1, "angle": 1.39, "curve": 0.243, "c3": 0.655, "c4": 0.63 },
					{ "time": 1.3333, "angle": 0.34 }
				]
			},
			"Women-5": {
				"rotate": [
					{ "angle": 0.88, "curve": 0.363, "c2": 0.44, "c3": 0.755 },
					{ "time": 0.2, "curve": 0.25, "c3": 0.75 },
					{ "time": 0.5333, "angle": 2.05, "curve": 0.25, "c3": 0.75 },
					{ "time": 0.8667, "curve": 0.25, "c3": 0.75 },
					{ "time": 1.2, "angle": 1.39, "curve": 0.258, "c3": 0.619, "c4": 0.45 },
					{ "time": 1.3333, "angle": 0.88 }
				]
			},
			"Women-9": {
				"rotate": [
					{ "angle": -0.8, "curve": 0.382, "c2": 0.58, "c3": 0.731 },
					{ "time": 0.1, "curve": 0.25, "c3": 0.75 },
					{ "time": 0.4333, "angle": -3.29, "curve": 0.25, "c3": 0.75 },
					{ "time": 0.7667, "curve": 0.25, "c3": 0.75 },
					{ "time": 1.1, "angle": -3.29, "curve": 0.243, "c3": 0.655, "c4": 0.63 },
					{ "time": 1.3333, "angle": -0.8 }
				]
			},
			"Women-10": {
				"rotate": [
					{ "angle": -1.64, "curve": 0.375, "c2": 0.5, "c3": 0.75 },
					{ "time": 0.1667, "curve": 0.25, "c3": 0.75 },
					{ "time": 0.5, "angle": -3.29, "curve": 0.25, "c3": 0.75 },
					{ "time": 0.8333, "curve": 0.25, "c3": 0.75 },
					{ "time": 1.1667, "angle": -3.29, "curve": 0.25, "c3": 0.625, "c4": 0.5 },
					{ "time": 1.3333, "angle": -1.64 }
				]
			},
			"Women-11": {
				"rotate": [
					{ "angle": -2.49, "curve": 0.345, "c2": 0.37, "c3": 0.757 },
					{ "time": 0.2333, "curve": 0.25, "c3": 0.75 },
					{ "time": 0.5667, "angle": -3.29, "curve": 0.25, "c3": 0.75 },
					{ "time": 0.9, "curve": 0.25, "c3": 0.75 },
					{ "time": 1.2333, "angle": -3.29, "curve": 0.269, "c3": 0.618, "c4": 0.42 },
					{ "time": 1.3333, "angle": -2.49 }
				]
			},
			"Women-14": {
				"translate": [
					{ "curve": 0.25, "c3": 0.75 },
					{ "time": 0.3333, "x": -2.88, "y": 6.76, "curve": 0.25, "c3": 0.75 },
					{ "time": 0.6667, "curve": 0.25, "c3": 0.75 },
					{ "time": 1, "x": -2.88, "y": 6.76, "curve": 0.25, "c3": 0.75 },
					{ "time": 1.3333 }
				]
			}
		}
	},
	"Woman2": {
		"slots": {
			"Women-1": {
				"attachment": [
					{ "name": "Women-2" }
				]
			},
			"Women-2(1)": {
				"attachment": [
					{ "name": "Women-2(1)" }
				]
			},
			"branches": {
				"attachment": [
					{ "name": null }
				]
			},
			"branches2": {
				"attachment": [
					{ "name": null }
				]
			},
			"branches3": {
				"attachment": [
					{ "name": null }
				]
			},
			"cloth": {
				"attachment": [
					{ "name": null }
				]
			}
		},
		"bones": {
			"Women-2(1)": {
				"rotate": [
					{ "angle": -0.71, "curve": 0.382, "c2": 0.57, "c3": 0.737 },
					{ "time": 0.3667, "curve": 0.25, "c3": 0.75 },
					{ "time": 1.3667, "angle": -2.34, "curve": 0.244, "c3": 0.646, "c4": 0.59 },
					{ "time": 2, "angle": -0.71 }
				]
			},
			"Women-14": {
				"rotate": [
					{ "angle": 0.53, "curve": 0.379, "c2": 0.6, "c3": 0.724 },
					{ "time": 0.2667, "curve": 0.25, "c3": 0.75 },
					{ "time": 1.2667, "angle": 2.88, "curve": 0.242, "c3": 0.667, "c4": 0.67 },
					{ "time": 2, "angle": 0.53 }
				],
				"translate": [
					{ "curve": 0.25, "c3": 0.75 },
					{ "time": 1, "x": -1.84, "y": 4.32, "curve": 0.25, "c3": 0.75 },
					{ "time": 2 }
				]
			},
			"Women-3": {
				"rotate": [
					{ "curve": 0.25, "c3": 0.75 },
					{ "time": 1, "angle": -1.18, "curve": 0.25, "c3": 0.75 },
					{ "time": 2 }
				]
			},
			"Women-4": {
				"rotate": [
					{ "angle": -0.12, "curve": 0.371, "c2": 0.62, "c3": 0.71 },
					{ "time": 0.1667, "curve": 0.25, "c3": 0.75 },
					{ "time": 1.1667, "angle": -1.2, "curve": 0.243, "c3": 0.689, "c4": 0.75 },
					{ "time": 2, "angle": -0.12 }
				]
			},
			"Women-5": {
				"rotate": [
					{ "angle": -1, "curve": 0.38, "c2": 0.59, "c3": 0.727 },
					{ "time": 0.2667, "curve": 0.25, "c3": 0.75 },
					{ "time": 1.2667, "angle": -4.94, "curve": 0.242, "c3": 0.663, "c4": 0.65 },
					{ "time": 2, "angle": -1 }
				]
			},
			"Women-9": {
				"rotate": [
					{ "angle": -0.71, "curve": 0.382, "c2": 0.57, "c3": 0.737 },
					{ "time": 0.3667, "curve": 0.25, "c3": 0.75 },
					{ "time": 1.3667, "angle": -2.34, "curve": 0.244, "c3": 0.646, "c4": 0.59 },
					{ "time": 2, "angle": -0.71 }
				]
			},
			"Women-10": {
				"rotate": [
					{ "angle": -2.72, "curve": 0.375, "c2": 0.5, "c3": 0.75 },
					{ "time": 0.5, "curve": 0.25, "c3": 0.75 },
					{ "time": 1.5, "angle": -5.44, "curve": 0.25, "c3": 0.625, "c4": 0.5 },
					{ "time": 2, "angle": -2.72 }
				]
			},
			"Women-11": {
				"rotate": [
					{ "angle": -6.61, "curve": 0.354, "c2": 0.41, "c3": 0.756 },
					{ "time": 0.6667, "curve": 0.25, "c3": 0.75 },
					{ "time": 1.6667, "angle": -9.51, "curve": 0.263, "c3": 0.618, "c4": 0.43 },
					{ "time": 2, "angle": -6.61 }
				]
			},
			"Women-2(1)2": {
				"rotate": [
					{ "angle": -2.36, "curve": 0.379, "c2": 0.52, "c3": 0.747 },
					{ "time": 0.4667, "curve": 0.25, "c3": 0.75 },
					{ "time": 1.4667, "angle": -5.44, "curve": 0.247, "c3": 0.63, "c4": 0.53 },
					{ "time": 2, "angle": -2.36 }
				]
			}
		}
	}
}
}